{
  "guests": [
    {
      "id": 1,
      "name": "John Stamos",
      "age": 58,
      "favoriteDish": "Sweet Potatoes",
      "rightHanded": true,
      "imageUrl": "https://encrypted-tbn0.gstatic.com/images?q=tbn:ANd9GcRswV8rkX_9XlysOOUTijtVzzLvvpGHynHcQQ&usqp=CAU"
    },
    {
      "id": 2,
      "name": "James Bond",
      "age": 40,
      "favoriteDish": "Shaken Dirties",
      "rightHanded": false,
      "imageUrl": "https://hips.hearstapps.com/hmg-prod.s3.amazonaws.com/images/irish-actor-pierce-brosnan-as-james-bond-in-a-publicity-news-photo-138084872-1551742467.jpg?crop=1xw:1xh;center,top&resize=480:*"
    },
    {
      "id": 3,
      "name": "Adele",
      "age": 33,
      "favoriteDish": "Sweet Potatoes",
      "rightHanded": false,
      "imageUrl": "https://encrypted-tbn0.gstatic.com/images?q=tbn:ANd9GcQhGQRcW2nVnJNW7rQOayUs5zvVYlqLkZMJIg&usqp=CAU"
    },
    {
      "name": "Jeremy Camp ",
      "age": "43",
      "favoriteDish": "Pumpkin Pie",
      "rightHanded": "true",
      "imageUrl": "https://morriscenter.org/wp-content/uploads/2019/11/Jeremy-Camp.jpg",
      "id": 4
    },
    {
      "name": "Jeremy Camp ",
      "age": "43",
      "favoriteDish": "Shaken Dirties",
      "rightHanded": "true",
      "imageUrl": "https://morriscenter.org/wp-content/uploads/2019/11/Jeremy-Camp.jpg",
      "id": 5
    },
    {
      "name": "Jeremy Camp ",
      "age": "43",
      "favoriteDish": "Sweet Potatoes",
      "rightHanded": "false",
      "imageUrl": "https://morriscenter.org/wp-content/uploads/2019/11/Jeremy-Camp.jpg",
      "id": 6
    }
  ]
}